{
  "extends": "./base.json",
  "compilerOptions": {
    "paths": {
      "@adapter/vue": [
        "packages/adapter/vue/vue2.7"
      ],
      "@adapter/vue/*": [
        "packages/adapter/vue/vue2.7/*"
      ],
      "@adapter/hooks": [
        "packages/adapter/hooks/vue2.7"
      ],
      "@adapter/hooks/*": [
        "packages/adapter/hooks/vue2.7/*"
      ],
      "@adapter/utils": [
        "packages/adapter/utils/vue2.7"
      ],
      "@adapter/utils/*": [
        "packages/adapter/utils/vue2.7/*"
      ],
      "@td/intel": [
        "packages/intel/vue2.7/src"
      ],
      "@td/intel/*": [
        "packages/intel/vue2.7/src/*"
      ],
      "@td/components": [
        "packages/components/vue2.7"
      ]
    }
  }
}
